letterhead_pdf/__init__.py
letterhead_pdf/__main__.py
letterhead_pdf/exceptions.py
letterhead_pdf/log_config.py
letterhead_pdf/main.py
letterhead_pdf/markdown_processor.py
letterhead_pdf/mcp_server.py
letterhead_pdf/pdf_merger.py
letterhead_pdf/pdf_utils.py
letterhead_pdf/installation/__init__.py
letterhead_pdf/installation/applescript_generator.py
letterhead_pdf/installation/droplet_builder.py
letterhead_pdf/installation/macos_integration.py
letterhead_pdf/installation/resource_manager.py
letterhead_pdf/installation/validator.py
letterhead_pdf/installation/templates/unified_droplet.applescript
letterhead_pdf/resources/Mac-letterhead.icns
letterhead_pdf/resources/__init__.py
letterhead_pdf/resources/defaults.css
letterhead_pdf/resources/icon.png
mac_letterhead-0.14.0.dist-info/METADATA
mac_letterhead-0.14.0.dist-info/WHEEL
mac_letterhead-0.14.0.dist-info/entry_points.txt
mac_letterhead-0.14.0.dist-info/licenses/LICENSE
mac_letterhead-0.14.0.dist-info/RECORD
