Metadata-Version: 2.4
Name: Mac-letterhead
Version: 0.14.0
Summary: A macOS utility to merge letterhead with PDF documents using a drag-and-drop interface
Author: Erik
License-Expression: MIT
License-File: LICENSE
Requires-Python: >=3.10
Requires-Dist: cffi>=1.15.0
Requires-Dist: cssselect2>=0.7.0
Requires-Dist: fonttools>=4.38.0
Requires-Dist: html5lib==1.1
Requires-Dist: importlib-resources; python_version < '3.9'
Requires-Dist: markdown>=3.7
Requires-Dist: pillow==11.1.0
Requires-Dist: pycmarkgfm>=1.2.0
Requires-Dist: pydyf>=0.5.0
Requires-Dist: pygments>=2.16.0
Requires-Dist: pymupdf==1.25.4
Requires-Dist: pyobjc-core==11.0
Requires-Dist: pyobjc-framework-cocoa==11.0
Requires-Dist: pyobjc-framework-quartz==11.0
Requires-Dist: pyphen>=0.13.0
Requires-Dist: reportlab>=3.6.0
Requires-Dist: six==1.16.0
Requires-Dist: tinycss2>=1.2.0
Requires-Dist: weasyprint==65.0
Requires-Dist: webencodings==0.5.1
Provides-Extra: dev
Requires-Dist: pytest-cov>=4.0.0; extra == 'dev'
Requires-Dist: pytest>=7.0.0; extra == 'dev'
Provides-Extra: markdown
Provides-Extra: mcp
Requires-Dist: mcp>=1.0.0; extra == 'mcp'
